simplpy/__init__.py
simplpy/dict_/__init__.py
simplpy/dict_/dict_func.py
simplpy/list_/__init__.py
simplpy/list_/list_func.py
simplpy/pd_/__init__.py
simplpy/pd_/pd_func.py
simplpy/sklearn_/__init__.py
simplpy/sklearn_/sklearn_func.py
simplpy-0.1a1.dist-info/LICENSE
simplpy-0.1a1.dist-info/METADATA
simplpy-0.1a1.dist-info/WHEEL
simplpy-0.1a1.dist-info/top_level.txt
simplpy-0.1a1.dist-info/RECORD
